{"events":[{"params":[0],"name":"Camera Movement","time":0},{"params":["powers",""],"time":0,"name":"HScript Call"},{"params":["1","0:0:8","linear","Out"],"time":0,"name":"Tween Camera Zoom"},{"params":["2"],"name":"Set Camera Speed","time":0},{"params":["powers",""],"time":3265.30612244898,"name":"HScript Call"},{"params":["powers",""],"time":4897.95918367347,"name":"HScript Call"},{"params":["powers",""],"name":"HScript Call","time":6530.61224489796},{"params":["powers",""],"name":"HScript Call","time":9795.91836734694},{"params":["powers",""],"time":11428.5714285714,"name":"HScript Call"},{"params":["0.75","0:2:0","quad","Out"],"name":"Tween Camera Zoom","time":13061.2244897959},{"params":["0.8"],"name":"Set Camera Zoom","time":15510.2040816327},{"params":["0.75"],"name":"Set Camera Zoom","time":16326.5306122449},{"params":[1],"name":"Camera Movement","time":19591.8367346939},{"params":["0.85","2:0:0","quad","Out"],"name":"Tween Camera Zoom","time":19591.8367346939},{"params":[],"name":"Toggle Snappy Camera","time":22857.1428571429},{"params":[0],"name":"Camera Movement","time":22857.1428571429},{"params":[1],"name":"Camera Movement","time":23469.387755102},{"params":[],"name":"Toggle Snappy Camera","time":23673.4693877551},{"params":["0.85","1:0:0","quad","Out"],"name":"Tween Camera Zoom","time":25306.1224489796},{"params":["0.75","2:0:0","quad","Out"],"name":"Tween Camera Zoom","time":26122.4489795918},{"params":[2],"name":"Camera Movement","time":26122.4489795918},{"params":["bgchange","1"],"name":"HScript Call","time":26938.7755102041},{"params":["0.8","2:0:0","quad","Out"],"name":"Tween Camera Zoom","time":31836.7346938776},{"params":["bgchange","0"],"name":"HScript Call","time":32653.0612244898},{"params":[1],"name":"Camera Movement","time":32653.0612244898},{"params":["0.85","2:0:0","quad","Out"],"name":"Tween Camera Zoom","time":32653.0612244898},{"params":["0.9"],"name":"Set Camera Zoom","time":35918.3673469388},{"params":["-3"],"name":"Set Camera Angle","time":35918.3673469388},{"params":["1"],"time":36326.5306122449,"name":"Set Camera Zoom"},{"params":["6"],"name":"Set Camera Angle","time":36326.5306122449},{"params":["0.85"],"name":"Set Camera Zoom","time":36734.693877551},{"params":["-3"],"name":"Set Camera Angle","time":36734.693877551},{"params":["1"],"time":37142.8571428571,"name":"Set Camera Zoom"},{"params":["3"],"time":37142.8571428571,"name":"Set Camera Angle"},{"params":["0.8"],"name":"Set Camera Zoom","time":37551.0204081633},{"params":["0.95","8:0:0","quad","Out"],"name":"Tween Camera Zoom","time":37551.0204081633},{"params":["bgchange","1"],"name":"HScript Call","time":38367.3469387755},{"params":[174],"time":39183.6734693878,"name":"BPM Change"},{"params":["bgchange","0"],"name":"HScript Call","time":39183.6734693878},{"params":[],"name":"Toggle Snappy Camera","time":39183.6734693878},{"params":["-3"],"name":"Set Camera Angle","time":39183.6734693878},{"params":[0],"name":"Camera Movement","time":39183.6734693878},{"params":["2.1","0"],"name":"logo","time":39183.6734693878},{"params":[1],"name":"Camera Movement","time":44700.9148486981},{"params":["3"],"name":"Set Camera Angle","time":44700.9148486981},{"params":["-3"],"name":"Set Camera Angle","time":50218.1562280085},{"params":[0],"name":"Camera Movement","time":50218.1562280085},{"params":["3"],"name":"Set Camera Angle","time":55735.3976073188},{"params":[1],"name":"Camera Movement","time":55735.3976073188},{"params":["bgchange","2"],"name":"HScript Call","time":61252.6389866291},{"params":["0"],"time":61252.6389866291,"name":"Set Camera Angle"},{"params":[],"name":"Toggle Snappy Camera","time":61252.6389866291},{"params":["0.5"],"name":"Set Camera Speed","time":61252.6389866291},{"params":[1],"time":61252.6389866291,"name":"Camera Movement"},{"params":[true,-1,9,"camHUD"],"time":64700.9148486981,"name":"Camera Flash"},{"params":["painting",1,true],"time":64700.9148486981,"name":"Play Sound"},{"params":["itsover",""],"name":"HScript Call","time":65390.5700211119},{"params":["welcomeback",""],"name":"HScript Call","time":72976.7769176636}],"codenameChart":true,"strumLines":[{"keyCount":4,"strumScale":1,"position":"boyfriend","notes":[{"id":1,"sLen":0,"time":13061.2244897959,"type":0},{"id":0,"sLen":0,"time":14081.6326530612,"type":0},{"id":2,"sLen":204.081632653062,"time":14285.7142857143,"type":0},{"id":0,"sLen":0,"time":14897.9591836735,"type":0},{"id":3,"sLen":0,"time":15102.0408163265,"type":0},{"id":0,"sLen":0,"time":15306.1224489796,"type":0},{"id":2,"sLen":0,"time":15510.2040816327,"type":0},{"id":0,"sLen":0,"time":15918.3673469388,"type":0},{"id":1,"sLen":204.08163265306,"time":15918.3673469388,"type":0},{"id":3,"sLen":0,"time":16326.5306122449,"type":0},{"id":3,"sLen":0,"time":17346.9387755102,"type":0},{"id":2,"sLen":204.081632653062,"time":17551.0204081633,"type":0},{"id":1,"sLen":0,"time":18163.2653061224,"type":0},{"id":1,"sLen":0,"time":18367.3469387755,"type":0},{"id":3,"sLen":0,"time":18571.4285714286,"type":0},{"id":2,"sLen":204.081632653062,"time":18775.5102040816,"type":0},{"id":2,"sLen":204.081632653062,"time":19183.6734693878,"type":0},{"id":1,"sLen":0,"time":19591.8367346939,"type":0},{"id":1,"sLen":0,"time":26530.612244898,"type":0},{"id":0,"sLen":0,"time":26734.693877551,"type":0},{"id":1,"sLen":0,"time":26938.7755102041,"type":0},{"id":2,"sLen":0,"time":28163.2653061225,"type":0},{"id":1,"sLen":0,"time":28367.3469387755,"type":0},{"id":3,"sLen":306.122448979593,"time":28571.4285714286,"type":0},{"id":0,"sLen":0,"time":28979.5918367347,"type":0},{"id":3,"sLen":306.122448979593,"time":29387.7551020408,"type":0},{"id":0,"sLen":0,"time":30408.1632653061,"type":0},{"id":0,"sLen":306.122448979586,"time":30612.2448979592,"type":0},{"id":1,"sLen":0,"time":31020.4081632653,"type":0},{"id":3,"sLen":0,"time":31428.5714285714,"type":0},{"id":0,"sLen":0,"time":31836.7346938776,"type":0},{"id":2,"sLen":306.122448979593,"time":31836.7346938776,"type":0},{"id":1,"sLen":0,"time":32244.8979591837,"type":0},{"id":1,"sLen":0,"time":32448.9795918367,"type":0},{"id":1,"sLen":0,"time":39183.6734693878,"type":0},{"id":2,"sLen":0,"time":39356.0872624912,"type":0},{"id":0,"sLen":0,"time":39528.5010555947,"type":0},{"id":3,"sLen":0,"time":39614.7079521464,"type":0},{"id":1,"sLen":0,"time":39700.9148486981,"type":0},{"id":2,"sLen":0,"time":39873.3286418015,"type":0},{"id":0,"sLen":0,"time":40045.742434905,"type":0},{"id":2,"sLen":0,"time":40218.1562280084,"type":0},{"id":3,"sLen":0,"time":40218.1562280084,"type":0},{"id":2,"sLen":0,"time":40562.9838142153,"type":0},{"id":0,"sLen":0,"time":40735.3976073188,"type":0},{"id":1,"sLen":0,"time":40907.8114004222,"type":0},{"id":3,"sLen":0,"time":40907.8114004222,"type":0},{"id":0,"sLen":0,"time":41080.2251935257,"type":0},{"id":3,"sLen":0,"time":41252.6389866291,"type":0},{"id":2,"sLen":0,"time":41425.0527797326,"type":0},{"id":0,"sLen":0,"time":41597.466572836,"type":0},{"id":1,"sLen":0,"time":41597.466572836,"type":0},{"id":2,"sLen":0,"time":41942.2941590429,"type":0},{"id":1,"sLen":0,"time":42114.7079521464,"type":0},{"id":3,"sLen":0,"time":42287.1217452498,"type":0},{"id":0,"sLen":0,"time":42373.3286418015,"type":0},{"id":1,"sLen":0,"time":42459.5355383533,"type":0},{"id":2,"sLen":0,"time":42631.9493314567,"type":0},{"id":0,"sLen":0,"time":42804.3631245602,"type":0},{"id":2,"sLen":0,"time":42976.7769176636,"type":0},{"id":3,"sLen":0,"time":42976.7769176636,"type":0},{"id":0,"sLen":0,"time":43321.6045038705,"type":0},{"id":2,"sLen":0,"time":43321.6045038705,"type":0},{"id":1,"sLen":0,"time":43494.018296974,"type":0},{"id":2,"sLen":0,"time":43666.4320900774,"type":0},{"id":0,"sLen":0,"time":43838.8458831809,"type":0},{"id":2,"sLen":0,"time":44011.2596762843,"type":0},{"id":3,"sLen":0,"time":44097.466572836,"type":0},{"id":2,"sLen":0,"time":44183.6734693878,"type":0},{"id":0,"sLen":0,"time":44356.0872624912,"type":0},{"id":1,"sLen":0,"time":44356.0872624912,"type":0},{"id":1,"sLen":0,"time":50218.1562280085,"type":0},{"id":2,"sLen":0,"time":50390.5700211119,"type":0},{"id":3,"sLen":0,"time":50562.9838142153,"type":0},{"id":0,"sLen":0,"time":50735.3976073188,"type":0},{"id":2,"sLen":0,"time":50735.3976073188,"type":0},{"id":1,"sLen":0,"time":51080.2251935257,"type":0},{"id":3,"sLen":0,"time":51252.6389866291,"type":0},{"id":2,"sLen":0,"time":51338.8458831809,"type":0},{"id":3,"sLen":0,"time":51425.0527797326,"type":0},{"id":1,"sLen":0,"time":51597.466572836,"type":0},{"id":2,"sLen":0,"time":51769.8803659395,"type":0},{"id":0,"sLen":0,"time":51942.2941590429,"type":0},{"id":2,"sLen":0,"time":52114.7079521464,"type":0},{"id":0,"sLen":0,"time":52287.1217452498,"type":0},{"id":1,"sLen":0,"time":52287.1217452498,"type":0},{"id":3,"sLen":0,"time":52631.9493314567,"type":0},{"id":1,"sLen":0,"time":52976.7769176636,"type":0},{"id":2,"sLen":0,"time":53149.1907107671,"type":0},{"id":3,"sLen":0,"time":53321.6045038705,"type":0},{"id":0,"sLen":0,"time":53494.018296974,"type":0},{"id":2,"sLen":0,"time":53494.018296974,"type":0},{"id":1,"sLen":0,"time":53838.8458831809,"type":0},{"id":2,"sLen":0,"time":54011.2596762843,"type":0},{"id":0,"sLen":0,"time":54183.6734693878,"type":0},{"id":1,"sLen":0,"time":54356.0872624912,"type":0},{"id":2,"sLen":0,"time":54528.5010555947,"type":0},{"id":3,"sLen":0,"time":54614.7079521464,"type":0},{"id":1,"sLen":0,"time":54700.9148486981,"type":0},{"id":2,"sLen":0,"time":54873.3286418016,"type":0},{"id":0,"sLen":0,"time":54959.5355383533,"type":0},{"id":1,"sLen":0,"time":55045.742434905,"type":0},{"id":3,"sLen":0,"time":55218.1562280085,"type":0},{"id":1,"sLen":0,"time":55304.3631245602,"type":0},{"id":2,"sLen":0,"time":55390.5700211119,"type":0}],"characters":["safestman"],"type":0,"visible":false,"strumPos":[0,50],"vocalsSuffix":"-slenderman","strumLinePos":0.25},{"keyCount":4,"strumScale":1,"position":"dad","notes":[{"id":0,"sLen":0,"time":19795.9183673469,"type":0},{"id":3,"sLen":0,"time":19897.9591836735,"type":0},{"id":2,"sLen":0,"time":20000,"type":0},{"id":0,"sLen":0,"time":20204.0816326531,"type":0},{"id":3,"sLen":0,"time":20408.1632653061,"type":0},{"id":1,"sLen":0,"time":20612.2448979592,"type":0},{"id":2,"sLen":0,"time":20816.3265306122,"type":0},{"id":0,"sLen":0,"time":21020.4081632653,"type":0},{"id":1,"sLen":0,"time":21224.4897959184,"type":0},{"id":0,"sLen":0,"time":21632.6530612245,"type":0},{"id":3,"sLen":0,"time":21836.7346938776,"type":0},{"id":1,"sLen":0,"time":21938.7755102041,"type":0},{"id":2,"sLen":0,"time":22040.8163265306,"type":0},{"id":0,"sLen":0,"time":22244.8979591837,"type":0},{"id":2,"sLen":204.081632653062,"time":22448.9795918367,"type":0},{"id":3,"sLen":0,"time":22448.9795918367,"type":0},{"id":1,"sLen":0,"time":23469.387755102,"type":0},{"id":0,"sLen":0,"time":23571.4285714286,"type":0},{"id":2,"sLen":0,"time":23673.4693877551,"type":0},{"id":1,"sLen":0,"time":23877.5510204082,"type":0},{"id":2,"sLen":204.081632653058,"time":24081.6326530612,"type":0},{"id":3,"sLen":0,"time":24081.6326530612,"type":0},{"id":0,"sLen":0,"time":24693.8775510204,"type":0},{"id":0,"sLen":0,"time":24897.9591836735,"type":0},{"id":1,"sLen":0,"time":25102.0408163265,"type":0},{"id":2,"sLen":0,"time":25306.1224489796,"type":0},{"id":0,"sLen":0,"time":25510.2040816327,"type":0},{"id":1,"sLen":0,"time":25714.2857142857,"type":0},{"id":2,"sLen":0,"time":25816.3265306122,"type":0},{"id":0,"sLen":0,"time":25918.3673469388,"type":0},{"id":1,"sLen":0,"time":26020.4081632653,"type":0},{"id":2,"sLen":204.081632653062,"time":26122.4489795918,"type":0},{"id":3,"sLen":0,"time":26122.4489795918,"type":0},{"id":1,"sLen":0,"time":27142.8571428571,"type":0},{"id":1,"sLen":306.122448979593,"time":27346.9387755102,"type":0},{"id":1,"sLen":0,"time":27346.9387755102,"type":0},{"id":3,"sLen":306.122448979593,"time":27755.1020408163,"type":0},{"id":0,"sLen":0,"time":28367.3469387755,"type":0},{"id":0,"sLen":306.122448979593,"time":28571.4285714286,"type":0},{"id":2,"sLen":306.122448979586,"time":28979.5918367347,"type":0},{"id":3,"sLen":306.122448979593,"time":29387.7551020408,"type":0},{"id":1,"sLen":0,"time":32857.1428571429,"type":0},{"id":0,"sLen":0,"time":33061.2244897959,"type":0},{"id":3,"sLen":0,"time":33265.306122449,"type":0},{"id":1,"sLen":0,"time":33469.387755102,"type":0},{"id":3,"sLen":0,"time":33673.4693877551,"type":0},{"id":0,"sLen":0,"time":33877.5510204082,"type":0},{"id":3,"sLen":0,"time":33979.5918367347,"type":0},{"id":0,"sLen":0,"time":34081.6326530612,"type":0},{"id":1,"sLen":0,"time":34489.7959183674,"type":0},{"id":3,"sLen":0,"time":34693.8775510204,"type":0},{"id":2,"sLen":0,"time":34897.9591836735,"type":0},{"id":0,"sLen":0,"time":35068.0272108843,"type":0},{"id":1,"sLen":0,"time":35102.0408163265,"type":0},{"id":3,"sLen":0,"time":35306.1224489796,"type":0},{"id":0,"sLen":0,"time":35510.2040816327,"type":0},{"id":3,"sLen":0,"time":35612.2448979592,"type":0},{"id":2,"sLen":0,"time":35714.2857142857,"type":0},{"id":1,"sLen":0,"time":35918.3673469388,"type":0},{"id":0,"sLen":0,"time":36122.4489795918,"type":0},{"id":2,"sLen":0,"time":36224.4897959184,"type":0},{"id":1,"sLen":0,"time":36326.5306122449,"type":0},{"id":3,"sLen":0,"time":36530.612244898,"type":0},{"id":0,"sLen":0,"time":36632.6530612245,"type":0},{"id":1,"sLen":0,"time":36734.693877551,"type":0},{"id":3,"sLen":0,"time":36938.7755102041,"type":0},{"id":2,"sLen":0,"time":37040.8163265306,"type":0},{"id":1,"sLen":0,"time":37142.8571428571,"type":0},{"id":3,"sLen":0,"time":37346.9387755102,"type":0},{"id":0,"sLen":0,"time":37551.0204081633,"type":0},{"id":3,"sLen":0,"time":37959.1836734694,"type":0},{"id":1,"sLen":0,"time":38367.3469387755,"type":0},{"id":0,"sLen":0,"time":38469.387755102,"type":0},{"id":1,"sLen":0,"time":38775.5102040816,"type":0},{"id":2,"sLen":0,"time":44700.9148486981,"type":0},{"id":0,"sLen":0,"time":44873.3286418015,"type":0},{"id":1,"sLen":0,"time":45045.742434905,"type":0},{"id":0,"sLen":0,"time":45131.9493314567,"type":0},{"id":1,"sLen":0,"time":45218.1562280085,"type":0},{"id":2,"sLen":0,"time":45390.5700211119,"type":0},{"id":3,"sLen":0,"time":45390.5700211119,"type":0},{"id":1,"sLen":0,"time":45562.9838142153,"type":0},{"id":2,"sLen":0,"time":45735.3976073188,"type":0},{"id":3,"sLen":0,"time":45735.3976073188,"type":0},{"id":0,"sLen":0,"time":46080.2251935257,"type":0},{"id":2,"sLen":0,"time":46252.6389866291,"type":0},{"id":3,"sLen":0,"time":46338.8458831809,"type":0},{"id":1,"sLen":0,"time":46425.0527797326,"type":0},{"id":0,"sLen":0,"time":46597.466572836,"type":0},{"id":2,"sLen":0,"time":46769.8803659395,"type":0},{"id":3,"sLen":0,"time":46856.0872624912,"type":0},{"id":0,"sLen":0,"time":46942.2941590429,"type":0},{"id":2,"sLen":0,"time":47028.5010555947,"type":0},{"id":1,"sLen":0,"time":47114.7079521464,"type":0},{"id":2,"sLen":0,"time":47459.5355383533,"type":0},{"id":0,"sLen":0,"time":47631.9493314567,"type":0},{"id":3,"sLen":0,"time":47804.3631245602,"type":0},{"id":1,"sLen":0,"time":47890.5700211119,"type":0},{"id":0,"sLen":0,"time":47976.7769176636,"type":0},{"id":2,"sLen":0,"time":48149.1907107671,"type":0},{"id":3,"sLen":0,"time":48149.1907107671,"type":0},{"id":0,"sLen":0,"time":48321.6045038705,"type":0},{"id":2,"sLen":0,"time":48494.018296974,"type":0},{"id":3,"sLen":0,"time":48494.018296974,"type":0},{"id":0,"sLen":0,"time":48666.4320900774,"type":0},{"id":1,"sLen":0,"time":48752.6389866291,"type":0},{"id":2,"sLen":0,"time":48838.8458831809,"type":0},{"id":3,"sLen":0,"time":49011.2596762843,"type":0},{"id":0,"sLen":0,"time":49097.466572836,"type":0},{"id":1,"sLen":0,"time":49183.6734693878,"type":0},{"id":3,"sLen":0,"time":49356.0872624912,"type":0},{"id":0,"sLen":0,"time":49528.5010555947,"type":0},{"id":1,"sLen":0,"time":49614.7079521464,"type":0},{"id":3,"sLen":0,"time":49700.9148486981,"type":0},{"id":1,"sLen":0,"time":49787.1217452498,"type":0},{"id":0,"sLen":0,"time":49873.3286418016,"type":0},{"id":2,"sLen":0,"time":49959.5355383533,"type":0},{"id":3,"sLen":0,"time":50045.742434905,"type":0},{"id":2,"sLen":0,"time":50131.9493314567,"type":0},{"id":0,"sLen":258.62068965529,"time":50218.1562280085,"type":0},{"id":2,"sLen":0,"time":55735.3976073188,"type":0},{"id":3,"sLen":0,"time":55735.3976073188,"type":0},{"id":1,"sLen":0,"time":55907.8114004222,"type":0},{"id":3,"sLen":0,"time":56080.2251935257,"type":0},{"id":0,"sLen":0,"time":56252.6389866291,"type":0},{"id":1,"sLen":0,"time":56597.466572836,"type":0},{"id":3,"sLen":0,"time":56942.2941590429,"type":0},{"id":2,"sLen":0,"time":57028.5010555947,"type":0},{"id":0,"sLen":0,"time":57114.7079521464,"type":0},{"id":1,"sLen":0,"time":57287.1217452498,"type":0},{"id":2,"sLen":258.620689655167,"time":57631.9493314567,"type":0},{"id":0,"sLen":0,"time":57976.7769176636,"type":0},{"id":3,"sLen":0,"time":58149.1907107671,"type":0},{"id":1,"sLen":0,"time":58321.6045038705,"type":0},{"id":0,"sLen":0,"time":58494.018296974,"type":0},{"id":3,"sLen":0,"time":58666.4320900774,"type":0},{"id":0,"sLen":0,"time":58752.6389866291,"type":0},{"id":2,"sLen":0,"time":58838.8458831809,"type":0},{"id":3,"sLen":0,"time":58838.8458831809,"type":0},{"id":1,"sLen":0,"time":59011.2596762843,"type":0},{"id":2,"sLen":0,"time":59183.6734693878,"type":0},{"id":3,"sLen":0,"time":59183.6734693878,"type":0},{"id":1,"sLen":0,"time":59356.0872624912,"type":0},{"id":0,"sLen":0,"time":59528.5010555947,"type":0},{"id":3,"sLen":0,"time":59873.3286418016,"type":0},{"id":0,"sLen":0,"time":59959.5355383533,"type":0},{"id":1,"sLen":0,"time":60045.742434905,"type":0},{"id":0,"sLen":0,"time":60131.9493314567,"type":0},{"id":2,"sLen":0,"time":60218.1562280085,"type":0},{"id":3,"sLen":0,"time":60304.3631245602,"type":0},{"id":0,"sLen":0,"time":60390.5700211119,"type":0},{"id":3,"sLen":0,"time":60476.7769176636,"type":0},{"id":1,"sLen":0,"time":60562.9838142153,"type":0},{"id":3,"sLen":0,"time":60735.3976073188,"type":0},{"id":0,"sLen":0,"time":60821.6045038705,"type":0},{"id":2,"sLen":0,"time":60907.8114004222,"type":0}],"characters":["marioyoussef1111"],"type":1,"visible":true,"strumPos":[0,50],"vocalsSuffix":"-marioyoussef","strumLinePos":0.5},{"keyCount":4,"strumScale":1,"position":"girlfriend","notes":[],"characters":["sorryNothing"],"type":2,"visible":false,"strumPos":[0,50],"vocalsSuffix":"","strumLinePos":1}],"scrollSpeed":3,"chartVersion":"1.6.0","stage":"slender","noteTypes":[]}